{"genie":{"genie1":{"ranking":1,"name":"봄여름가을겨울 (Still Life)","singer":"BIGBANG (빅뱅)","album":"봄여름가을겨울 (Still Life)","id":"genie1","publisher":"YG PLUS","agency":"YG Entertainment"},"genie2":{"ranking":2,"name":"TOMBOY","singer":"(여자)아이들","album":"I NEVER DIE","id":"genie2","publisher":"카카오엔터테인먼트","agency":"큐브 엔터테인먼트"},"genie3":{"ranking":3,"name":"LOVE DIVE","singer":"IVE (아이브)","album":"LOVE DIVE","id":"genie3","publisher":"카카오엔터테인먼트","agency":"스타쉽 엔터테인먼트"},"genie4":{"ranking":4,"name":"Feel My Rhythm","singer":"Red Velvet (레드벨벳)","album":"'The ReVe Festival 2022 - Feel My Rhythm'","id":"genie4","publisher":"Dreamus","agency":"SM ENTERTAINMENT"},"genie5":{"ranking":5,"name":"사랑인가 봐","singer":"멜로망스 (MeloMance)","album":"사랑인가 봐 (사내맞선 OST 스페셜 트랙)","id":"genie5","publisher":"카카오엔터테인먼트","agency":"플렉스엠"},"genie6":{"ranking":6,"name":"GANADARA (Feat. 아이유)","singer":"박재범","album":"GANADARA","id":"genie6","publisher":"카카오엔터테인먼트","agency":"MORE VISION"},"genie7":{"ranking":7,"name":"취중고백","singer":"김민석 (멜로망스)","album":"취중고백","id":"genie7","publisher":"워너뮤직","agency":"프로젝트 리본"},"genie8":{"ranking":8,"name":"듣고 싶을까","singer":"MSG워너비 (M.O.M)","album":"듣고 싶을까","id":"genie8","publisher":"지니뮤직, Stone Music Entertainment","agency":"문화방송"},"genie9":{"ranking":9,"name":"INVU","singer":"태연 (TAEYEON)","album":"INVU - The 3rd Album","id":"genie9","publisher":"Dreamus","agency":"SM ENTERTAINMENT"},"genie10":{"ranking":10,"name":"사랑은 늘 도망가","singer":"임영웅","album":"신사와 아가씨 OST Part.2","id":"genie10","publisher":"NHN벅스","agency":"모스트콘텐츠"},"genie11":{"ranking":11,"name":"신호등","singer":"이무진","album":"신호등","id":"genie11","publisher":"카카오엔터테인먼트","agency":"쇼플레이엔터테인먼트"},"genie12":{"ranking":12,"name":"LOVE me","singer":"BE'O (비오)","album":"LOVE me","id":"genie12","publisher":"카카오엔터테인먼트","agency":"BPM ENTERTAINMENT, SWING ENTERTAINMENT, 페임어스 엔터테인먼트"},"genie13":{"ranking":13,"name":"회전목마 (Feat. Zion.T & 원슈타인) (Prod. by Slom)","singer":"sokodomo","album":"쇼미더머니 10 Episode 2","id":"genie13","publisher":"지니뮤직","agency":"Stone Music Entertainment"},"genie14":{"ranking":14,"name":"다정히 내 이름을 부르면","singer":"경서예지 & 전건호","album":"다정히 내 이름을 부르면 (경서예지 x 전건호)","id":"genie14","publisher":"카카오엔터테인먼트","agency":"에버그로우"},"genie15":{"ranking":15,"name":"ELEVEN","singer":"IVE (아이브)","album":"ELEVEN","id":"genie15","publisher":"카카오엔터테인먼트","agency":"스타쉽 엔터테인먼트"},"genie16":{"ranking":16,"name":"abcdefu","singer":"GAYLE","album":"abcdefu","id":"genie16","publisher":"워너뮤직","agency":"Atlantic, Arthouse Records"},"genie17":{"ranking":17,"name":"Stay","singer":"The Kid LAROI & Justin Bieber","album":"Stay","id":"genie17","publisher":"Sony Music","agency":"Columbia"},"genie18":{"ranking":18,"name":"strawberry moon","singer":"아이유 (IU)","album":"strawberry moon","id":"genie18","publisher":"카카오엔터테인먼트","agency":"EDAM엔터테인먼트"},"genie19":{"ranking":19,"name":"언제나 사랑해","singer":"케이시 (Kassy)","album":"조영수 리메이크 프로젝트 Part.2","id":"genie19","publisher":"카카오엔터테인먼트","agency":"도토리뮤직"},"genie20":{"ranking":20,"name":"리무진 (Feat. MINO) (Prod. by GRAY)","singer":"BE'O (비오)","album":"쇼미더머니 10 Episode 3","id":"genie20","publisher":"지니뮤직","agency":"Stone Music Entertainment"},"genie21":{"ranking":21,"name":"스물다섯, 스물하나","singer":"자우림","album":"Goodbye, grief.","id":"genie21","publisher":"㈜인터파크","agency":"자우림"},"genie22":{"ranking":22,"name":"흔들리는 꽃들 속에서 네 샴푸향이 느껴진거야","singer":"장범준","album":"멜로가 체질 OST Part 3 (JTBC 금토 드라마)","id":"genie22","publisher":"지니뮤직, Stone Music Entertainment","agency":"Stone Music Entertainment, 삼화네트웍스"},"genie23":{"ranking":23,"name":"이제 나만 믿어요","singer":"임영웅","album":"내일은 미스터트롯 우승자 특전곡","id":"genie23","publisher":"카카오엔터테인먼트","agency":"TV CHOSUN"},"genie24":{"ranking":24,"name":"Stronger (What Doesn't Kill You)","singer":"Kelly Clarkson","album":"Stronger (What Doesn't Kill You) (Digital Audio Bundle)","id":"genie24","publisher":"Sony Music","agency":""},"genie25":{"ranking":25,"name":"RUN2U","singer":"STAYC (스테이씨)","album":"YOUNG-LUV.COM","id":"genie25","publisher":"카카오엔터테인먼트","agency":"HIGHUP ENTERTAINMENT"},"genie26":{"ranking":26,"name":"다시 사랑한다면 (김필 Ver.)","singer":"임영웅","album":"사랑의 콜센타 PART56","id":"genie26","publisher":"카카오엔터테인먼트","agency":"TV CHOSUN, ㈜쇼플레이"},"genie27":{"ranking":27,"name":"Next Level","singer":"aespa","album":"Next Level","id":"genie27","publisher":"Dreamus","agency":"SM ENTERTAINMENT"},"genie28":{"ranking":28,"name":"Weekend","singer":"태연 (TAEYEON)","album":"Weekend","id":"genie28","publisher":"Dreamus","agency":"SM ENTERTAINMENT"},"genie29":{"ranking":29,"name":"내 손을 잡아","singer":"아이유 (IU)","album":"최고의 사랑 OST Part.4 (MBC 수목드라마)","id":"genie29","publisher":"카카오엔터테인먼트","agency":"더그루브엔터테인먼트 (더그루브컴퍼니)"},"genie30":{"ranking":30,"name":"어제처럼","singer":"폴킴","album":"어제처럼","id":"genie30","publisher":"카카오엔터테인먼트","agency":"메모리즈 프로젝트"},"genie31":{"ranking":31,"name":"너를 생각해","singer":"주시크 (Joosiq)","album":"너를 생각해","id":"genie31","publisher":"워너뮤직","agency":"주식회사 레시피뮤직"},"genie32":{"ranking":32,"name":"라일락","singer":"아이유 (IU)","album":"IU 5th Album 'LILAC'","id":"genie32","publisher":"카카오엔터테인먼트","agency":"EDAM엔터테인먼트"},"genie33":{"ranking":33,"name":"SMILEY (Feat. BIBI)","singer":"YENA (최예나)","album":"SMiLEY","id":"genie33","publisher":"지니뮤직, Stone Music Entertainment","agency":"위에화엔터테인먼트코리아"},"genie34":{"ranking":34,"name":"OHAYO MY NIGHT","singer":"디핵 (D-Hack) & PATEKO","album":"OHAYO MY NIGHT","id":"genie34","publisher":"YG PLUS","agency":"NEOKIDZ"},"genie35":{"ranking":35,"name":"Bad Habits","singer":"Ed Sheeran","album":"=","id":"genie35","publisher":"워너뮤직","agency":"Atlantic Records UK"},"genie36":{"ranking":36,"name":"호랑수월가","singer":"탑현","album":"호랑수월가","id":"genie36","publisher":"카카오엔터테인먼트","agency":"탑현월드"},"genie37":{"ranking":37,"name":"Counting Stars (Feat. Beenzino)","singer":"BE'O (비오)","album":"Counting Stars","id":"genie37","publisher":"지니뮤직, Stone Music Entertainment","agency":"페임어스 엔터테인먼트"},"genie38":{"ranking":38,"name":"Celebrity","singer":"아이유 (IU)","album":"IU 5th Album 'LILAC'","id":"genie38","publisher":"카카오엔터테인먼트","agency":"EDAM엔터테인먼트"},"genie39":{"ranking":39,"name":"바라만 본다","singer":"MSG워너비 (M.O.M)","album":"MSG워너비 1집","id":"genie39","publisher":"지니뮤직, Stone Music Entertainment","agency":"유야호"},"genie40":{"ranking":40,"name":"별빛 같은 나의 사랑아","singer":"임영웅","album":"별빛 같은 나의 사랑아","id":"genie40","publisher":"카카오엔터테인먼트","agency":"티조컬처앤컨텐츠, 뉴에라프로젝트, 물고기뮤직"},"genie41":{"ranking":41,"name":"MY BAG","singer":"(여자)아이들","album":"I NEVER DIE","id":"genie41","publisher":"카카오엔터테인먼트","agency":"큐브 엔터테인먼트"},"genie42":{"ranking":42,"name":"잊었니","singer":"임영웅","album":"사랑의 콜센타 PART60","id":"genie42","publisher":"카카오엔터테인먼트","agency":"TV CHOSUN, ㈜쇼플레이"},"genie43":{"ranking":43,"name":"Dynamite","singer":"방탄소년단","album":"Dynamite (DayTime Ver.)","id":"genie43","publisher":"YG PLUS","agency":"BIGHIT MUSIC"},"genie44":{"ranking":44,"name":"드라마","singer":"아이유 (IU)","album":"조각집","id":"genie44","publisher":"카카오엔터테인먼트","agency":"EDAM엔터테인먼트"},"genie45":{"ranking":45,"name":"그대라는 사치","singer":"임영웅","album":"사랑의 콜센타 PART62","id":"genie45","publisher":"카카오엔터테인먼트","agency":"TV CHOSUN, ㈜쇼플레이"},"genie46":{"ranking":46,"name":"벚꽃 엔딩","singer":"버스커 버스커 (Busker Busker)","album":"버스커 버스커 1집","id":"genie46","publisher":"지니뮤직","agency":"Stone Music Entertainment"},"genie47":{"ranking":47,"name":"끝사랑","singer":"임영웅","album":"사랑의 콜센타 PART61","id":"genie47","publisher":"카카오엔터테인먼트","agency":"TV CHOSUN, ㈜쇼플레이"},"genie48":{"ranking":48,"name":"문득","singer":"BE'O (비오)","album":"Bipolar","id":"genie48","publisher":"지니뮤직, Stone Music Entertainment","agency":"페임어스 엔터테인먼트"},"genie49":{"ranking":49,"name":"서랍","singer":"10CM","album":"그 해 우리는 OST Part.1","id":"genie49","publisher":"NHN벅스","agency":"모스트콘텐츠"},"genie50":{"ranking":50,"name":"Blueming","singer":"아이유 (IU)","album":"Love poem","id":"genie50","publisher":"카카오엔터테인먼트","agency":"카카오엔터테인먼트"},"genie51":{"ranking":51,"name":"HERO","singer":"임영웅","album":"HERO","id":"genie51","publisher":"카카오엔터테인먼트","agency":"티조컬처앤컨텐츠, 뉴에라프로젝트"},"genie52":{"ranking":52,"name":"Step Back","singer":"GOT the beat","album":"Step Back","id":"genie52","publisher":"Dreamus","agency":"SM ENTERTAINMENT"},"genie53":{"ranking":53,"name":"우연히 봄","singer":"로꼬 & 유주 (YUJU)","album":"냄새를 보는 소녀 OST Part.2 (SBS 수목드라마)","id":"genie53","publisher":"카카오엔터테인먼트","agency":"(주)도너츠컬처"},"genie54":{"ranking":54,"name":"너의 모든 순간","singer":"성시경","album":"별에서 온 그대 OST Part.7 (SBS 수목드라마)","id":"genie54","publisher":"NHN벅스","agency":"㈜SBS콘텐츠허브 (㈜에스비에스콘텐츠허브)"},"genie55":{"ranking":55,"name":"내가 아니라도","singer":"주호","album":"내가 아니라도","id":"genie55","publisher":"워너뮤직","agency":"IN A MILLION"},"genie56":{"ranking":56,"name":"존재만으로","singer":"원슈타인","album":"스물다섯 스물하나 OST Part 4","id":"genie56","publisher":"YG PLUS","agency":"스튜디오 마음C, 화앤담픽쳐스"},"genie57":{"ranking":57,"name":"Tiny Riot","singer":"Sam Ryder","album":"The Sun's Gonna Rise","id":"genie57","publisher":"워너뮤직","agency":"Parlophone UK"},"genie58":{"ranking":58,"name":"Bk Love","singer":"임영웅","album":"뽕숭아학당 PART23","id":"genie58","publisher":"카카오엔터테인먼트","agency":"TV CHOSUN, ㈜쇼플레이"},"genie59":{"ranking":59,"name":"나는 트로트가 싫어요","singer":"임창정","album":"별거 없던 그 하루로","id":"genie59","publisher":"㈜인터파크","agency":"YES IM ENTERTAINMENT"},"genie60":{"ranking":60,"name":"Butter","singer":"방탄소년단","album":"Butter","id":"genie60","publisher":"YG PLUS","agency":"BIGHIT MUSIC"},"genie61":{"ranking":61,"name":"Real Love","singer":"오마이걸 (OH MY GIRL)","album":"Real Love","id":"genie61","publisher":"Sony Music","agency":"WM엔터테인먼트"},"genie62":{"ranking":62,"name":"만남은 쉽고 이별은 어려워 (Feat. Leellamarz) (Prod. by TOIL)","singer":"베이식 (Basick)","album":"쇼미더머니 10 Episode 3","id":"genie62","publisher":"지니뮤직","agency":"Stone Music Entertainment"},"genie63":{"ranking":63,"name":"눈이 오잖아 (Feat. 헤이즈)","singer":"이무진","album":"눈이 오잖아","id":"genie63","publisher":"카카오엔터테인먼트","agency":"쇼플레이엔터테인먼트"},"genie64":{"ranking":64,"name":"찰나가 영원이 될 때 (The Eternal Moment)","singer":"마크툽 (Maktub)","album":"Red Moon : Beyond The Light","id":"genie64","publisher":"워너뮤직","agency":"(주)MAKTUB Company"},"genie65":{"ranking":65,"name":"너의 번호를 누르고","singer":"김나영","album":"너의 번호를 누르고","id":"genie65","publisher":"NHN벅스","agency":"니즈뮤직"},"genie66":{"ranking":66,"name":"2002","singer":"Anne-Marie","album":"Speak Your Mind (Deluxe)","id":"genie66","publisher":"워너뮤직","agency":"Atlantic Records UK"},"genie67":{"ranking":67,"name":"My Universe","singer":"Coldplay & 방탄소년단","album":"My Universe","id":"genie67","publisher":"워너뮤직","agency":"Parlophone UK"},"genie68":{"ranking":68,"name":"고백","singer":"멜로망스 (MeloMance)","album":"세 번째 '고백'","id":"genie68","publisher":"카카오엔터테인먼트","agency":"카카오엔터테인먼트, 민트페이퍼, 광합성"},"genie69":{"ranking":69,"name":"봄 사랑 벚꽃 말고","singer":"HIGH4 & 아이유","album":"봄 사랑 벚꽃 말고","id":"genie69","publisher":"카카오엔터테인먼트","agency":"엔에이피엔터테인먼트"},"genie70":{"ranking":70,"name":"Savage","singer":"aespa","album":"Savage - The 1st Mini Album","id":"genie70","publisher":"Dreamus","agency":"SM ENTERTAINMENT"},"genie71":{"ranking":71,"name":"낙하 (With 아이유)","singer":"AKMU (악뮤)","album":"NEXT EPISODE","id":"genie71","publisher":"YG PLUS","agency":"YG Entertainment"},"genie72":{"ranking":72,"name":"Darl＋ing","singer":"세븐틴 (SEVENTEEN)","album":"Darl＋ing","id":"genie72","publisher":"YG PLUS","agency":"플레디스 엔터테인먼트"},"genie73":{"ranking":73,"name":"Starlight","singer":"태일 (TAEIL)","album":"스물다섯 스물하나 OST Part 1","id":"genie73","publisher":"YG PLUS","agency":"스튜디오 마음C, 화앤담픽쳐스"},"genie74":{"ranking":74,"name":"니 소식2","singer":"송하예","album":"니 소식2 X 송하예","id":"genie74","publisher":"카카오엔터테인먼트","agency":"빅오션이엔엠"},"genie75":{"ranking":75,"name":"Off My Face","singer":"Justin Bieber","album":"Justice","id":"genie75","publisher":"Universal Music","agency":"Def Jam Recordings, a division of UMG Recordings, Inc"},"genie76":{"ranking":76,"name":"밤하늘의 별을 (2020)","singer":"경서","album":"밤하늘의 별을 (2020)","id":"genie76","publisher":"카카오엔터테인먼트","agency":"꿈의 엔진"},"genie77":{"ranking":77,"name":"에잇 (Prod. & Feat. SUGA of BTS)","singer":"아이유 (IU)","album":"에잇","id":"genie77","publisher":"카카오엔터테인먼트","agency":"EDAM엔터테인먼트"},"genie78":{"ranking":78,"name":"At My Worst","singer":"Pink Sweat$","album":"The Prelude","id":"genie78","publisher":"워너뮤직","agency":"Atlantic Records"},"genie79":{"ranking":79,"name":"모든 날, 모든 순간 (Every day, Every Moment)","singer":"폴킴","album":"'키스 먼저 할까요?' OST Part. 3 (SBS 월화드라마)","id":"genie79","publisher":"Dreamus","agency":"SM ENTERTAINMENT"},"genie80":{"ranking":80,"name":"아로하","singer":"조정석","album":"슬기로운 의사생활 OST Part 3 (tvN 목요드라마)","id":"genie80","publisher":"지니뮤직, Stone Music Entertainment","agency":"스튜디오 마음C, 에그이즈커밍, Stone Music Entertainment"},"genie81":{"ranking":81,"name":"계단말고 엘리베이터","singer":"임영웅","album":"계단말고 엘리베이터","id":"genie81","publisher":"뮤직앤뉴","agency":"물고기뮤직"},"genie82":{"ranking":82,"name":"Permission to Dance","singer":"방탄소년단","album":"Butter / Permission to Dance","id":"genie82","publisher":"YG PLUS","agency":"BIGHIT MUSIC"},"genie83":{"ranking":83,"name":"사이렌 Remix (Feat. UNEDUCATED KID & Paul Blanco)","singer":"호미들","album":"사이렌 Remix","id":"genie83","publisher":"카카오엔터테인먼트","agency":"영앤리치 레코즈"},"genie84":{"ranking":84,"name":"헤픈 우연","singer":"헤이즈 (Heize)","album":"HAPPEN","id":"genie84","publisher":"지니뮤직, Stone Music Entertainment","agency":"피네이션"},"genie85":{"ranking":85,"name":"Because Of You","singer":"Ne-Yo","album":"Because Of You","id":"genie85","publisher":"Universal Music","agency":""},"genie86":{"ranking":86,"name":"롤린 (Rollin')","singer":"브레이브걸스 (Brave girls)","album":"Rollin'","id":"genie86","publisher":"3.14","agency":"브레이브엔터테인먼트 (BRAVE ENTERTAINMENT)"},"genie87":{"ranking":87,"name":"아무래도 난","singer":"주시크 (Joosiq)","album":"아무래도 난","id":"genie87","publisher":"워너뮤직","agency":"주식회사 레시피뮤직"},"genie88":{"ranking":88,"name":"오늘도 빛나는 너에게 (To You My Light) (Feat.이라온)","singer":"마크툽 (Maktub)","album":"Red Moon : To You My Light","id":"genie88","publisher":"워너뮤직","agency":"(주)MAKTUB Company"},"genie89":{"ranking":89,"name":"겨울잠","singer":"아이유 (IU)","album":"조각집","id":"genie89","publisher":"카카오엔터테인먼트","agency":"EDAM엔터테인먼트"},"genie90":{"ranking":90,"name":"버퍼링 (Glitch Mode)","singer":"NCT DREAM","album":"Glitch Mode - The 2nd Album","id":"genie90","publisher":"Dreamus","agency":"SM ENTERTAINMENT"},"genie91":{"ranking":91,"name":"Peaches (Feat. Daniel Caesar & Giveon)","singer":"Justin Bieber","album":"Justice","id":"genie91","publisher":"Universal Music","agency":"Def Jam Recordings, a division of UMG Recordings, Inc"},"genie92":{"ranking":92,"name":"DAYDREAM","singer":"하이라이트 (Highlight)","album":"DAYDREAM","id":"genie92","publisher":"카카오엔터테인먼트","agency":"어라운드 어스"},"genie93":{"ranking":93,"name":"Dreams Come True","singer":"aespa","album":"Dreams Come True - SM STATION","id":"genie93","publisher":"Dreamus","agency":"SM ENTERTAINMENT"},"genie94":{"ranking":94,"name":"Hey Mama (Feat. Nicki Minaj & Bebe Rexha & Afrojack)","singer":"David Guetta","album":"Listen (Deluxe)","id":"genie94","publisher":"워너뮤직","agency":"Parlophone France"},"genie95":{"ranking":95,"name":"Dun Dun Dance","singer":"오마이걸 (OH MY GIRL)","album":"Dear OHMYGIRL","id":"genie95","publisher":"Sony Music","agency":"WM Entertainment"},"genie96":{"ranking":96,"name":"오래된 노래","singer":"Standing Egg (스탠딩 에그)","album":"오래된 노래","id":"genie96","publisher":"카카오엔터테인먼트","agency":"본(born)"},"genie97":{"ranking":97,"name":"선물","singer":"멜로망스 (MeloMance)","album":"Moonlight","id":"genie97","publisher":"카카오엔터테인먼트","agency":"민트페이퍼, 광합성"},"genie98":{"ranking":98,"name":"Loving You Girl (Feat. Hkeem)","singer":"Peder Elias","album":"Loving You Girl","id":"genie98","publisher":"Sony Music","agency":"Columbia"},"genie99":{"ranking":99,"name":"12 : 45 (Stripped)","singer":"etham","album":"12 : 45 (Stripped)","id":"genie99","publisher":"Universal Music","agency":"Closer Recordings Limited"},"genie100":{"ranking":100,"name":"너, 너 (N번째 연애 X 휘인 (Whee In))","singer":"휘인 (Whee In)","album":"너, 너 (N번째 연애 X 휘인 (Whee In))","id":"genie100","publisher":"카카오엔터테인먼트","agency":"TOON STUDIO"},"genie101":{"ranking":101,"name":"어떻게 이별까지 사랑하겠어, 널 사랑하는 거지","singer":"AKMU (악뮤)","album":"항해","id":"genie101","publisher":"YG PLUS","agency":"(주)YG엔터테인먼트"},"genie102":{"ranking":102,"name":"잊을 수 있을까","singer":"노을","album":"이별을 말하는","id":"genie102","publisher":"워너뮤직","agency":"말하는"},"genie103":{"ranking":103,"name":"벚꽃이 피면 우리 그만 헤어져","singer":"벤","album":"벚꽃이 피면 우리 그만 헤어져","id":"genie103","publisher":"지니뮤직","agency":"메이저나인"},"genie104":{"ranking":104,"name":"그래서 그래 (Feat. 윤하)","singer":"에픽하이 (EPIK HIGH)","album":"Epik High Is Here 下","id":"genie104","publisher":"지니뮤직","agency":"(주)아워즈"},"genie105":{"ranking":105,"name":"Savage Love (Laxed - Siren Beat) (BTS Remix)","singer":"Jawsh 685 & Jason Derulo & 방탄소년단","album":"Savage Love (Laxed - Siren Beat) (BTS Remix)","id":"genie105","publisher":"Sony Music","agency":"Columbia"},"genie106":{"ranking":106,"name":"있잖아","singer":"폴킴","album":"연애플레이리스트2 OST Part.2","id":"genie106","publisher":"3.14","agency":"스페이스오디티"},"genie107":{"ranking":107,"name":"우리가 헤어져야 했던 이유","singer":"비비 (BIBI)","album":"그 해 우리는 OST Part.2","id":"genie107","publisher":"NHN벅스","agency":"모스트콘텐츠"},"genie108":{"ranking":108,"name":"노래 (The Song)","singer":"비투비","album":"Be Together","id":"genie108","publisher":"카카오엔터테인먼트","agency":"큐브 엔터테인먼트"},"genie109":{"ranking":109,"name":"밝게 빛나는 별이 되어 비춰줄게","singer":"송이한","album":"밝게 빛나는 별이 되어 비춰줄게","id":"genie109","publisher":"카카오엔터테인먼트","agency":"㈜뮤직디자인"},"genie110":{"ranking":110,"name":"너의 번호를 누르고 (Prod. by 영화처럼)","singer":"#안녕","album":"너의 번호를 누르고","id":"genie110","publisher":"워너뮤직","agency":"니즈먼트"},"genie111":{"ranking":111,"name":"비와 당신","singer":"이무진","album":"슬기로운 의사생활 시즌2 OST Part 1 (tvN 목요드라마)","id":"genie111","publisher":"지니뮤직, Stone Music Entertainment","agency":"스튜디오 마음C, 에그이즈커밍, Stone Music Entertainment"},"genie112":{"ranking":112,"name":"흰눈","singer":"먼데이 키즈 (Monday Kiz)","album":"흰눈","id":"genie112","publisher":"워너뮤직","agency":"프로젝트 리본"},"genie113":{"ranking":113,"name":"봄이 좋냐??","singer":"10CM","album":"3.2","id":"genie113","publisher":"포크라노스","agency":"매직스트로베리사운드"},"genie114":{"ranking":114,"name":"그게 더 편할 것 같아 (N번째 연애 X 멜로망스)","singer":"멜로망스 (MeloMance)","album":"그게 더 편할 것 같아 (N번째 연애 X 멜로망스)","id":"genie114","publisher":"카카오엔터테인먼트","agency":"TOON STUDIO"},"genie115":{"ranking":115,"name":"작은 것들을 위한 시 (Boy With Luv) (Feat. Halsey)","singer":"방탄소년단","album":"MAP OF THE SOUL : PERSONA","id":"genie115","publisher":"YG PLUS","agency":"BIGHIT MUSIC"},"genie116":{"ranking":116,"name":"추억은 만남보다 이별에 남아","singer":"정동하","album":"추억은 만남보다 이별에 남아","id":"genie116","publisher":"카카오엔터테인먼트","agency":"뮤직원 컴퍼니"},"genie117":{"ranking":117,"name":"parachute","singer":"John K","album":"love ＋ everything else","id":"genie117","publisher":"Sony Music","agency":"Epic"},"genie118":{"ranking":118,"name":"That's Hilarious","singer":"Charlie Puth","album":"That's Hilarious","id":"genie118","publisher":"워너뮤직","agency":"Atlantic Records"},"genie119":{"ranking":119,"name":"METEOR","singer":"창모 (CHANGMO)","album":"Boyhood","id":"genie119","publisher":"지니뮤직, Stone Music Entertainment","agency":"Ambition Musik"},"genie120":{"ranking":120,"name":"Love Blossom (러브블러썸)","singer":"케이윌 (K.Will)","album":"The 3rd Album Part.2 'Love Blossom (러브블러썸)'","id":"genie120","publisher":"카카오엔터테인먼트","agency":"스타쉽 엔터테인먼트"},"genie121":{"ranking":121,"name":"Can't Control Myself","singer":"태연 (TAEYEON)","album":"Can't Control Myself","id":"genie121","publisher":"Dreamus","agency":"SM ENTERTAINMENT"},"genie122":{"ranking":122,"name":"Memories","singer":"Maroon 5","album":"Memories","id":"genie122","publisher":"Universal Music","agency":"Interscope Records (222 Records)"},"genie123":{"ranking":123,"name":"Every Second","singer":"Mina Okabe","album":"Every Second","id":"genie123","publisher":"Universal Music","agency":"Universal Music (Denmark) A/S"},"genie124":{"ranking":124,"name":"쉬어 (Feat. MINO) (Prod. by GRAY)","singer":"아넌딜라이트 (Anandelight) & Unofficialboyy & BE'O (비오) & 지구인 & Mudd The Student","album":"쇼미더머니 10 Episode 1","id":"genie124","publisher":"지니뮤직","agency":"Stone Music Entertainment"},"genie125":{"ranking":125,"name":"봄날","singer":"방탄소년단","album":"YOU NEVER WALK ALONE","id":"genie125","publisher":"YG PLUS","agency":"BIGHIT MUSIC"},"genie126":{"ranking":126,"name":"취기를 빌려 (취향저격 그녀 X 산들)","singer":"산들","album":"취기를 빌려 (취향저격 그녀 X 산들)","id":"genie126","publisher":"카카오엔터테인먼트","agency":"TOON STUDIO"},"genie127":{"ranking":127,"name":"Bad","singer":"Christopher","album":"Under the Surface","id":"genie127","publisher":"워너뮤직","agency":"Parlophone Denmark"},"genie128":{"ranking":128,"name":"Wake Up (Prod. by 코드 쿤스트)","singer":"개코 & 아우릴고트 (OUREALGOAT) & SINCE & 안병웅 & Tabber & 조광일","album":"쇼미더머니 10 Episode 1","id":"genie128","publisher":"지니뮤직","agency":"Stone Music Entertainment"},"genie129":{"ranking":129,"name":"상상더하기","singer":"라붐 (LABOUM)","album":"Fresh Adventure","id":"genie129","publisher":"㈜인터파크","agency":"주식회사 글로벌에이치미디어 (GLOBAL H)"},"genie130":{"ranking":130,"name":"마지막 너의 인사","singer":"헤이즈 (Heize)","album":"우리들의 블루스 OST Part 2","id":"genie130","publisher":"지니뮤직, Stone Music Entertainment","agency":"냠냠엔터테인먼트"},"genie131":{"ranking":131,"name":"비가 오는 날엔 (2021)","singer":"헤이즈 (Heize)","album":"비가 오는 날엔 (2021)","id":"genie131","publisher":"지니뮤직, Stone Music Entertainment","agency":"PLAYLIST"},"genie132":{"ranking":132,"name":"Timeless","singer":"SG워너비","album":"Wanna Be＋","id":"genie132","publisher":"지니뮤직","agency":"Stone Music Entertainment"},"genie133":{"ranking":133,"name":"Dance Monkey","singer":"Tones And I","album":"The Kids Are Coming","id":"genie133","publisher":"워너뮤직","agency":"Elektra (NEK)"},"genie134":{"ranking":134,"name":"Rock with you","singer":"세븐틴 (SEVENTEEN)","album":"SEVENTEEN 9th Mini Album 'Attacca'","id":"genie134","publisher":"YG PLUS","agency":"플레디스 엔터테인먼트"},"genie135":{"ranking":135,"name":"Rainy day (Feat. ASH ISLAND & Skinny Brown)","singer":"PATEKO (파테코)","album":"Rainy day","id":"genie135","publisher":"YG PLUS","agency":"tokkinny records"},"genie136":{"ranking":136,"name":"꽃 길","singer":"BIGBANG (빅뱅)","album":"꽃 길","id":"genie136","publisher":"YG PLUS","agency":"(주)YG엔터테인먼트"},"genie137":{"ranking":137,"name":"노래방에서","singer":"장범준","album":"장범준 3집","id":"genie137","publisher":"카카오엔터테인먼트","agency":"㈜버스커버스커"},"genie138":{"ranking":138,"name":"Kiss Me More (Feat. SZA)","singer":"Doja Cat","album":"Kiss Me More","id":"genie138","publisher":"Sony Music","agency":"Kemosabe Records, RCA Records"},"genie139":{"ranking":139,"name":"하늘바라기 (Feat. 하림)","singer":"정은지","album":"Dream","id":"genie139","publisher":"카카오엔터테인먼트","agency":"플랜에이 엔터테인먼트"},"genie140":{"ranking":140,"name":"그날에 나는 맘이 편했을까","singer":"이예준","album":"그날에 나는 맘이 편했을까","id":"genie140","publisher":"카카오엔터테인먼트","agency":"뮤니콘"},"genie141":{"ranking":141,"name":"Way Back Home","singer":"숀 (SHAUN)","album":"Take","id":"genie141","publisher":"워너뮤직","agency":"디씨톰엔터테인먼트"},"genie142":{"ranking":142,"name":"부럽지가 않어","singer":"장기하","album":"공중부양","id":"genie142","publisher":"카카오엔터테인먼트","agency":"두루두루 아티스트 컴퍼니"},"genie143":{"ranking":143,"name":"만개 (Prod. 신지후)","singer":"김호중","album":"우리家","id":"genie143","publisher":"카카오엔터테인먼트","agency":"생각을보여주는엔터테인먼트"},"genie144":{"ranking":144,"name":"시간을 거슬러 (낮에 뜨는 달 X 케이윌)","singer":"케이윌 (K.Will)","album":"시간을 거슬러 (낮에 뜨는 달 X 케이윌)","id":"genie144","publisher":"카카오엔터테인먼트","agency":"TOON STUDIO"},"genie145":{"ranking":145,"name":"시작","singer":"가호 (Gaho)","album":"이태원 클라쓰 OST Part.2 (JTBC 금토드라마)","id":"genie145","publisher":"주식회사 블렌딩","agency":"㈜블렌딩"},"genie146":{"ranking":146,"name":"O.O","singer":"NMIXX","album":"AD MARE","id":"genie146","publisher":"Dreamus","agency":"(주)JYP엔터테인먼트"},"genie147":{"ranking":147,"name":"Go!","singer":"도겸 (SEVENTEEN)","album":"스물다섯 스물하나 OST Part 5","id":"genie147","publisher":"YG PLUS","agency":"스튜디오 마음C, 화앤담픽쳐스"},"genie148":{"ranking":148,"name":"나보다 더 사랑해요","singer":"김호중","album":"나보다 더 사랑해요","id":"genie148","publisher":"카카오엔터테인먼트","agency":"생각을보여주는엔터테인먼트"},"genie149":{"ranking":149,"name":"멜로디","singer":"ASH ISLAND","album":"멜로디","id":"genie149","publisher":"지니뮤직, Stone Music Entertainment","agency":"앰비션뮤직"},"genie150":{"ranking":150,"name":"주저하는 연인들을 위해","singer":"잔나비","album":"전설","id":"genie150","publisher":"카카오엔터테인먼트","agency":"페포니 뮤직"},"genie151":{"ranking":151,"name":"좋은 사람 있으면 소개시켜줘","singer":"조이 (JOY)","album":"슬기로운 의사생활 OST Part 2 (tvN 목요드라마)","id":"genie151","publisher":"지니뮤직, Stone Music Entertainment","agency":"스튜디오 마음C, 에그이즈커밍, Stone Music Entertainment"},"genie152":{"ranking":152,"name":"밤편지","singer":"아이유 (IU)","album":"밤편지","id":"genie152","publisher":"카카오엔터테인먼트","agency":"카카오엔터테인먼트, ㈜페이브엔터테인먼트"},"genie153":{"ranking":153,"name":"네가 없는 밤 (Feat. ASH ISLAND) (Prod. by GRAY)","singer":"BE'O (비오)","album":"쇼미더머니 10 Final","id":"genie153","publisher":"지니뮤직","agency":"Stone Music Entertainment"},"genie154":{"ranking":154,"name":"찾았다 내 사랑","singer":"V.O.S","album":"찾았다 내 사랑","id":"genie154","publisher":"카카오엔터테인먼트","agency":"방구석 캐스팅"},"genie155":{"ranking":155,"name":"불협화음 (Feat. AKMU) (Prod. by GRAY)","singer":"Mudd the student","album":"쇼미더머니 10 Semi Final","id":"genie155","publisher":"지니뮤직","agency":"Stone Music Entertainment"},"genie156":{"ranking":156,"name":"좋아좋아","singer":"조정석","album":"슬기로운 의사생활 시즌2 OST Part 5 (tvN 목요드라마)","id":"genie156","publisher":"지니뮤직, Stone Music Entertainment","agency":"스튜디오 마음C, 에그이즈커밍, Stone Music Entertainment"},"genie157":{"ranking":157,"name":"첫눈처럼 너에게 가겠다","singer":"에일리 (Ailee)","album":"도깨비 OST Part 9 (tvN 금토드라마)","id":"genie157","publisher":"지니뮤직, Stone Music Entertainment","agency":"Stone Music Entertainment, 화앤담픽쳐스"},"genie158":{"ranking":158,"name":"운전만해 (We Ride)","singer":"브레이브걸스 (Brave girls)","album":"We Ride","id":"genie158","publisher":"카카오엔터테인먼트","agency":"브레이브엔터테인먼트 (BRAVE ENTERTAINMENT)"},"genie159":{"ranking":159,"name":"ZOOM","singer":"제시","album":"ZOOM","id":"genie159","publisher":"카카오엔터테인먼트","agency":"피네이션 주식회사"},"genie160":{"ranking":160,"name":"우산 (Feat. 윤하)","singer":"에픽하이 (EPIK HIGH)","album":"Breakdown","id":"genie160","publisher":"지니뮤직","agency":"Stone Music Entertainment"},"genie161":{"ranking":161,"name":"늦은 밤 너의 집 앞 골목길에서","singer":"노을","album":"늦은 밤 너의 집 앞 골목길에서","id":"genie161","publisher":"카카오엔터테인먼트","agency":"씨제스 엔터테인먼트 (C-JeS Entertainment)"},"genie162":{"ranking":162,"name":"Lovesick Girls","singer":"BLACKPINK","album":"THE ALBUM","id":"genie162","publisher":"YG PLUS","agency":"(주)YG엔터테인먼트"},"genie163":{"ranking":163,"name":"Shape Of You","singer":"Ed Sheeran","album":"÷ (Deluxe)","id":"genie163","publisher":"워너뮤직","agency":"Atlantic Records UK"},"genie164":{"ranking":164,"name":"어떻게 지내 (Prod. by VAN.C)","singer":"오반","album":"어떻게 지내","id":"genie164","publisher":"카카오엔터테인먼트","agency":"로맨틱팩토리"},"genie165":{"ranking":165,"name":"잠이 오질 않네요","singer":"장범준","album":"잠이 오질 않네요","id":"genie165","publisher":"카카오엔터테인먼트","agency":"㈜버스커버스커"},"genie166":{"ranking":166,"name":"마음을 드려요","singer":"아이유 (IU)","album":"사랑의 불시착 OST Part 11 (tvN 토일 드라마)","id":"genie166","publisher":"카카오엔터테인먼트","agency":"EDAM엔터테인먼트"},"genie167":{"ranking":167,"name":"ASAP","singer":"STAYC (스테이씨)","album":"STAYDOM","id":"genie167","publisher":"카카오엔터테인먼트","agency":"HIGHUP ENTERTAINMENT"},"genie168":{"ranking":168,"name":"친구라도 될 걸 그랬어","singer":"HYNN (박혜원)","album":"친구라도 될 걸 그랬어","id":"genie168","publisher":"YG PLUS","agency":"+기억 프로젝트"},"genie169":{"ranking":169,"name":"사랑인가 봐 (Acoustic Ver.)","singer":"김세정","album":"사랑인가 봐 (사내맞선 OST Bonus Track)","id":"genie169","publisher":"카카오엔터테인먼트","agency":"플렉스엠"},"genie170":{"ranking":170,"name":"어푸 (Ah puh)","singer":"아이유 (IU)","album":"IU 5th Album 'LILAC'","id":"genie170","publisher":"카카오엔터테인먼트","agency":"EDAM엔터테인먼트"},"genie171":{"ranking":171,"name":"Christmas Tree","singer":"V","album":"그 해 우리는 OST Part.5","id":"genie171","publisher":"NHN벅스","agency":"모스트콘텐츠"},"genie172":{"ranking":172,"name":"안녕","singer":"폴킴","album":"호텔 델루나 OST Part.10 (tvN 토일드라마)","id":"genie172","publisher":"Dreamus","agency":"냠냠엔터테인먼트"},"genie173":{"ranking":173,"name":"Light Switch","singer":"Charlie Puth","album":"That's Hilarious","id":"genie173","publisher":"워너뮤직","agency":"Atlantic Records"},"genie174":{"ranking":174,"name":"LOVE DAY (2021) (바른연애 길잡이 X 양요섭, 정은지)","singer":"양요섭 & 정은지","album":"LOVE DAY (2021) (바른연애 길잡이 X 양요섭, 정은지)","id":"genie174","publisher":"카카오엔터테인먼트","agency":"TOON STUDIO, 느을"},"genie175":{"ranking":175,"name":"북극성 (Never Goodbye)","singer":"NCT DREAM","album":"Glitch Mode - The 2nd Album","id":"genie175","publisher":"Dreamus","agency":"SM ENTERTAINMENT"},"genie176":{"ranking":176,"name":"Paris In The Rain","singer":"Lauv","album":"I met you when I was 18. (the playlist)","id":"genie176","publisher":"NHN벅스","agency":"뮤직테이블"},"genie177":{"ranking":177,"name":"희재","singer":"성시경","album":"국화꽃 향기 OST","id":"genie177","publisher":"(주)씨에스해피엔터테인먼트","agency":"씨에스해피엔터테인먼트"},"genie178":{"ranking":178,"name":"사랑인걸","singer":"한동근","album":"사랑인걸","id":"genie178","publisher":"카카오엔터테인먼트","agency":"방구석 캐스팅"},"genie179":{"ranking":179,"name":"사실 나는 (Feat. 전건호)","singer":"경서예지","album":"사실 나는","id":"genie179","publisher":"카카오엔터테인먼트","agency":"먼데이키즈 컴퍼니, 에버그로우"},"genie180":{"ranking":180,"name":"하루만 더","singer":"빅마마 (Big Mama)","album":"하루만 더","id":"genie180","publisher":"카카오엔터테인먼트","agency":"카카오엔터테인먼트"},"genie181":{"ranking":181,"name":"Beautiful Day","singer":"어반자카파","album":"Beautiful Day","id":"genie181","publisher":"뮤직앤뉴","agency":"플럭서스뮤직"},"genie182":{"ranking":182,"name":"Ashes","singer":"Stellar","album":"Ashes","id":"genie182","publisher":"Sony Music","agency":"Arista Records"},"genie183":{"ranking":183,"name":"서툰 이별을 하려해 (Feat. 전상근)","singer":"윤토벤 (YounToven)","album":"서툰 이별을 하려해","id":"genie183","publisher":"사운드리퍼블리카","agency":"윤토벤"},"genie184":{"ranking":184,"name":"With","singer":"김태리 & 남주혁 & 보나 (우주소녀) & 최현욱 & 이주명","album":"스물다섯 스물하나 OST Part 7","id":"genie184","publisher":"YG PLUS","agency":"스튜디오 마음C, 화앤담픽쳐스"},"genie185":{"ranking":185,"name":"고맙소","singer":"김호중","album":"내일은 미스터트롯 결승전 베스트","id":"genie185","publisher":"카카오엔터테인먼트","agency":"TV CHOSUN, ㈜쇼플레이"},"genie186":{"ranking":186,"name":"Queendom","singer":"Red Velvet (레드벨벳)","album":"Queendom - The 6th Mini Album","id":"genie186","publisher":"Dreamus","agency":"SM ENTERTAINMENT"},"genie187":{"ranking":187,"name":"Maniac","singer":"Conan Gray","album":"Maniac","id":"genie187","publisher":"Universal Music","agency":"Republic Records, a division of UMG Recordings, Inc."},"genie188":{"ranking":188,"name":"아주, 천천히","singer":"비비 (BIBI)","album":"스물다섯 스물하나 OST Part 3","id":"genie188","publisher":"YG PLUS","agency":"스튜디오 마음C, 화앤담픽쳐스"},"genie189":{"ranking":189,"name":"Leave The Door Open","singer":"Bruno Mars & Anderson .Paak & Silk Sonic","album":"An Evening With Silk Sonic","id":"genie189","publisher":"워너뮤직","agency":"Aftermath Entertainment, Atlantic"},"genie190":{"ranking":190,"name":"너, 너","singer":"스트레이 (The Stray)","album":"her","id":"genie190","publisher":"NHN벅스","agency":"파스텔뮤직"},"genie191":{"ranking":191,"name":"비 오는 날 듣기 좋은 노래 (Feat. Colde)","singer":"에픽하이 (EPIK HIGH)","album":"비 오는 날 듣기 좋은 노래","id":"genie191","publisher":"지니뮤직","agency":"(주)아워즈"},"genie192":{"ranking":192,"name":"Don't Start Now","singer":"Dua Lipa","album":"Future Nostalgia","id":"genie192","publisher":"워너뮤직","agency":"Warner Records"},"genie193":{"ranking":193,"name":"VVS (Feat. JUSTHIS) (Prod. by GroovyRoom)","singer":"미란이 (Mirani) & 먼치맨 (MUNCHMAN) & Khundi Panda & 머쉬베놈 (MUSHVENOM)","album":"쇼미더머니 9 Episode 1","id":"genie193","publisher":"지니뮤직","agency":"Stone Music Entertainment"},"genie194":{"ranking":194,"name":"한여름밤의 꿀 : 다시 여름","singer":"San E & 레이나","album":"한여름밤의 꿀 : 다시 여름 (TEN PROJECT Part.3)","id":"genie194","publisher":"NHN벅스","agency":"브랜뉴뮤직 (Brand New Music)"},"genie195":{"ranking":195,"name":"벌써 일년","singer":"브라운 아이즈","album":"Brown Eyes","id":"genie195","publisher":"지니뮤직, Stone Music Entertainment","agency":"갑엔터테인먼트"},"genie196":{"ranking":196,"name":"살았소","singer":"김호중","album":"살았소","id":"genie196","publisher":"카카오엔터테인먼트","agency":"생각을보여주는엔터테인먼트, 제이지스타"},"genie197":{"ranking":197,"name":"하루하루","singer":"BIGBANG (빅뱅)","album":"Stand Up (2008 빅뱅 3rd Mini Album)","id":"genie197","publisher":"YG PLUS","agency":"(주)YG엔터테인먼트"},"genie198":{"ranking":198,"name":"Crush","singer":"세븐틴 (SEVENTEEN)","album":"SEVENTEEN 9th Mini Album 'Attacca'","id":"genie198","publisher":"YG PLUS","agency":"플레디스 엔터테인먼트"},"genie199":{"ranking":199,"name":"Dolphin","singer":"오마이걸 (OH MY GIRL)","album":"NONSTOP","id":"genie199","publisher":"Sony Music","agency":"WM엔터테인먼트"},"genie200":{"ranking":200,"name":"치맛바람 (Chi Mat Ba Ram)","singer":"브레이브걸스 (Brave girls)","album":"Summer Queen","id":"genie200","publisher":"카카오엔터테인먼트","agency":"브레이브엔터테인먼트 (BRAVE ENTERTAINMENT)"},"update_time":"2022-04-17T08:33:01.372Z"}}